odoo/addons/l10n_ch_zip/README.rst
odoo/addons/l10n_ch_zip/__init__.py
odoo/addons/l10n_ch_zip/__manifest__.py
odoo/addons/l10n_ch_zip/data/res.better.zip.csv
odoo/addons/l10n_ch_zip/i18n/de.po
odoo/addons/l10n_ch_zip/i18n/fr.po
odoo/addons/l10n_ch_zip/i18n/it.po
odoo/addons/l10n_ch_zip/i18n/nb_NO.po
odoo/addons/l10n_ch_zip/i18n/nl.po
odoo/addons/l10n_ch_zip/models/__init__.py
odoo/addons/l10n_ch_zip/models/better_zip.py
odoo/addons/l10n_ch_zip/static/description/icon.png
odoo11_addon_l10n_ch_zip-11.0.1.0.0.dist-info/DESCRIPTION.rst
odoo11_addon_l10n_ch_zip-11.0.1.0.0.dist-info/METADATA
odoo11_addon_l10n_ch_zip-11.0.1.0.0.dist-info/RECORD
odoo11_addon_l10n_ch_zip-11.0.1.0.0.dist-info/WHEEL
odoo11_addon_l10n_ch_zip-11.0.1.0.0.dist-info/metadata.json
odoo11_addon_l10n_ch_zip-11.0.1.0.0.dist-info/top_level.txt
